[
  {
    "_id": {
      "$oid": "60d21b4667d0d8992e610cc0"
    },
    "orderNumber": "ORD-10001",
    "items": [
      {
        "part": {
          "$oid": "60d21b4667d0d8992e610ca0"
        },
        "quantity": 2,
        "price": 8.99
      },
      {
        "part": {
          "$oid": "60d21b4667d0d8992e610cb4"
        },
        "quantity": 1,
        "price": 24.99
      }
    ],
    "totalAmount": 42.97,
    "paymentMethod": "CARD",
    "status": "COMPLETED",
    "customerName": "John Smith",
    "customerPhone": "555-123-4567",
    "customerEmail": "john.smith@example.com",
    "carRegistration": "AB12 CDE",
    "createdAt": "2023-06-15T10:30:00.000Z",
    "user": {
      "$oid": "67d580341d40dbf5dfe6d761"
    }
  },
  {
    "_id": {
      "$oid": "60d21b4667d0d8992e610cc1"
    },
    "orderNumber": "ORD-10002",
    "items": [
      {
        "part": {
          "$oid": "60d21b4667d0d8992e610ca2"
        },
        "quantity": 1,
        "price": 35.99
      },
      {
        "part": {
          "$oid": "60d21b4667d0d8992e610ca3"
        },
        "quantity": 1,
        "price": 65.99
      }
    ],
    "totalAmount": 101.98,
    "paymentMethod": "CASH",
    "status": "COMPLETED",
    "customerName": "Sarah Johnson",
    "customerPhone": "555-234-5678",
    "customerEmail": "sarah.j@example.com",
    "carRegistration": "XY34 ZAB",
    "createdAt": "2023-06-16T14:45:00.000Z",
    "user": {
      "$oid": "67d580341d40dbf5dfe6d761"
    }
  },
  {
    "_id": {
      "$oid": "60d21b4667d0d8992e610cc2"
    },
    "orderNumber": "ORD-10003",
    "items": [
      {
        "part": {
          "$oid": "60d21b4667d0d8992e610ca5"
        },
        "quantity": 1,
        "price": 89.99
      }
    ],
    "totalAmount": 89.99,
    "paymentMethod": "CARD",
    "status": "COMPLETED",
    "customerName": "Michael Brown",
    "customerPhone": "555-345-6789",
    "customerEmail": "mbrown@example.com",
    "carRegistration": "CD45 EFG",
    "createdAt": "2023-06-18T09:15:00.000Z",
    "user": {
      "$oid": "67d580341d40dbf5dfe6d761"
    }
  },
  {
    "_id": {
      "$oid": "60d21b4667d0d8992e610cc3"
    },
    "orderNumber": "ORD-10004",
    "items": [
      {
        "part": {
          "$oid": "60d21b4667d0d8992e610ca4"
        },
        "quantity": 1,
        "price": 28.99
      },
      {
        "part": {
          "$oid": "60d21b4667d0d8992e610ca1"
        },
        "quantity": 1,
        "price": 12.99
      },
      {
        "part": {
          "$oid": "60d21b4667d0d8992e610ca0"
        },
        "quantity": 1,
        "price": 8.99
      }
    ],
    "totalAmount": 50.97,
    "paymentMethod": "CASH",
    "status": "COMPLETED",
    "customerName": "Emily Davis",
    "customerPhone": "555-456-7890",
    "customerEmail": "emily.davis@example.com",
    "carRegistration": "EF56 GHI",
    "createdAt": "2023-06-20T16:30:00.000Z",
    "user": {
      "$oid": "67d580341d40dbf5dfe6d761"
    }
  },
  {
    "_id": {
      "$oid": "60d21b4667d0d8992e610cc4"
    },
    "orderNumber": "ORD-10005",
    "items": [
      {
        "part": {
          "$oid": "60d21b4667d0d8992e610ca6"
        },
        "quantity": 1,
        "price": 129.99
      }
    ],
    "totalAmount": 129.99,
    "paymentMethod": "CARD",
    "status": "COMPLETED",
    "customerName": "David Wilson",
    "customerPhone": "555-567-8901",
    "customerEmail": "dwilson@example.com",
    "carRegistration": "GH67 IJK",
    "createdAt": "2023-06-22T11:20:00.000Z",
    "user": {
      "$oid": "67d580341d40dbf5dfe6d761"
    }
  },
  {
    "_id": {
      "$oid": "60d21b4667d0d8992e610cc5"
    },
    "orderNumber": "ORD-10006",
    "items": [
      {
        "part": {
          "$oid": "60d21b4667d0d8992e610cb6"
        },
        "quantity": 1,
        "price": 29.99
      }
    ],
    "totalAmount": 29.99,
    "paymentMethod": "CASH",
    "status": "COMPLETED",
    "customerName": "Jessica Martinez",
    "customerPhone": "555-678-9012",
    "createdAt": "2023-06-25T13:45:00.000Z",
    "user": {
      "$oid": "67d580341d40dbf5dfe6d761"
    }
  },
  {
    "_id": {
      "$oid": "60d21b4667d0d8992e610cc6"
    },
    "orderNumber": "ORD-10007",
    "items": [
      {
        "part": {
          "$oid": "60d21b4667d0d8992e610cb7"
        },
        "quantity": 1,
        "price": 49.99
      }
    ],
    "totalAmount": 49.99,
    "paymentMethod": "CARD",
    "status": "COMPLETED",
    "customerName": "Robert Taylor",
    "customerPhone": "555-789-0123",
    "createdAt": "2023-06-28T10:10:00.000Z",
    "user": {
      "$oid": "67d580341d40dbf5dfe6d761"
    }
  },
  {
    "_id": {
      "$oid": "60d21b4667d0d8992e610cc7"
    },
    "orderNumber": "ORD-10008",
    "items": [
      {
        "part": {
          "$oid": "60d21b4667d0d8992e610cb5"
        },
        "quantity": 2,
        "price": 8.99
      },
      {
        "part": {
          "$oid": "60d21b4667d0d8992e610cb4"
        },
        "quantity": 1,
        "price": 24.99
      }
    ],
    "totalAmount": 42.97,
    "paymentMethod": "CASH",
    "status": "COMPLETED",
    "customerName": "Jennifer Anderson",
    "customerPhone": "555-890-1234",
    "createdAt": "2023-07-01T15:30:00.000Z",
    "user": {
      "$oid": "67d580341d40dbf5dfe6d761"
    }
  },
  {
    "_id": {
      "$oid": "60d21b4667d0d8992e610cc8"
    },
    "orderNumber": "ORD-10009",
    "items": [
      {
        "part": {
          "$oid": "60d21b4667d0d8992e610ca7"
        },
        "quantity": 1,
        "price": 119.99
      },
      {
        "part": {
          "$oid": "60d21b4667d0d8992e610ca8"
        },
        "quantity": 1,
        "price": 49.99
      }
    ],
    "totalAmount": 169.98,
    "paymentMethod": "CARD",
    "status": "COMPLETED",
    "customerName": "Christopher Thomas",
    "customerPhone": "555-901-2345",
    "createdAt": "2023-07-05T09:45:00.000Z",
    "user": {
      "$oid": "67d580341d40dbf5dfe6d761"
    }
  },
  {
    "_id": {
      "$oid": "60d21b4667d0d8992e610cc9"
    },
    "orderNumber": "ORD-10010",
    "items": [
      {
        "part": {
          "$oid": "60d21b4667d0d8992e610ca9"
        },
        "quantity": 1,
        "price": 79.99
      }
    ],
    "totalAmount": 79.99,
    "paymentMethod": "CARD",
    "status": "COMPLETED",
    "customerName": "Amanda White",
    "customerPhone": "555-012-3456",
    "createdAt": "2023-07-08T14:20:00.000Z",
    "user": {
      "$oid": "67d580341d40dbf5dfe6d761"
    }
  },
  {
    "_id": {
      "$oid": "60d21b4667d0d8992e610cca"
    },
    "orderNumber": "ORD-10011",
    "items": [
      {
        "part": {
          "$oid": "60d21b4667d0d8992e610cab"
        },
        "quantity": 1,
        "price": 89.99
      }
    ],
    "totalAmount": 89.99,
    "paymentMethod": "CASH",
    "status": "COMPLETED",
    "customerName": "Daniel Harris",
    "customerPhone": "555-123-4568",
    "createdAt": "2023-07-10T11:15:00.000Z",
    "user": {
      "$oid": "67d580341d40dbf5dfe6d761"
    }
  },
  {
    "_id": {
      "$oid": "60d21b4667d0d8992e610ccb"
    },
    "orderNumber": "ORD-10012",
    "items": [
      {
        "part": {
          "$oid": "60d21b4667d0d8992e610cac"
        },
        "quantity": 1,
        "price": 19.99
      },
      {
        "part": {
          "$oid": "60d21b4667d0d8992e610ca1"
        },
        "quantity": 1,
        "price": 12.99
      }
    ],
    "totalAmount": 32.98,
    "paymentMethod": "CARD",
    "status": "COMPLETED",
    "customerName": "Melissa Clark",
    "customerPhone": "555-234-5679",
    "createdAt": "2023-07-12T16:40:00.000Z",
    "user": {
      "$oid": "67d580341d40dbf5dfe6d761"
    }
  },
  {
    "_id": {
      "$oid": "60d21b4667d0d8992e610ccc"
    },
    "orderNumber": "ORD-10013",
    "items": [
      {
        "part": {
          "$oid": "60d21b4667d0d8992e610cae"
        },
        "quantity": 1,
        "price": 49.99
      }
    ],
    "totalAmount": 49.99,
    "paymentMethod": "CASH",
    "status": "COMPLETED",
    "customerName": "Matthew Lewis",
    "customerPhone": "555-345-6780",
    "createdAt": "2023-07-15T10:30:00.000Z",
    "user": {
      "$oid": "67d580341d40dbf5dfe6d761"
    }
  },
  {
    "_id": {
      "$oid": "60d21b4667d0d8992e610ccd"
    },
    "orderNumber": "ORD-10014",
    "items": [
      {
        "part": {
          "$oid": "60d21b4667d0d8992e610caf"
        },
        "quantity": 2,
        "price": 45.99
      }
    ],
    "totalAmount": 91.98,
    "paymentMethod": "CARD",
    "status": "COMPLETED",
    "customerName": "Laura Walker",
    "customerPhone": "555-456-7891",
    "createdAt": "2023-07-18T13:15:00.000Z",
    "user": {
      "$oid": "67d580341d40dbf5dfe6d761"
    }
  },
  {
    "_id": {
      "$oid": "60d21b4667d0d8992e610cce"
    },
    "orderNumber": "ORD-10015",
    "items": [
      {
        "part": {
          "$oid": "60d21b4667d0d8992e610cb0"
        },
        "quantity": 1,
        "price": 189.99
      }
    ],
    "totalAmount": 189.99,
    "paymentMethod": "CARD",
    "status": "COMPLETED",
    "customerName": "James Hall",
    "customerPhone": "555-567-8902",
    "createdAt": "2023-07-20T09:50:00.000Z",
    "user": {
      "$oid": "67d580341d40dbf5dfe6d761"
    }
  },
  {
    "_id": {
      "$oid": "60d21b4667d0d8992e610ccf"
    },
    "orderNumber": "ORD-10016",
    "items": [
      {
        "part": {
          "$oid": "60d21b4667d0d8992e610cb1"
        },
        "quantity": 1,
        "price": 109.99
      }
    ],
    "totalAmount": 109.99,
    "paymentMethod": "CASH",
    "status": "COMPLETED",
    "customerName": "Patricia Young",
    "customerPhone": "555-678-9013",
    "createdAt": "2023-07-22T14:30:00.000Z",
    "user": {
      "$oid": "67d580341d40dbf5dfe6d761"
    }
  },
  {
    "_id": {
      "$oid": "60d21b4667d0d8992e610cd0"
    },
    "orderNumber": "ORD-10017",
    "items": [
      {
        "part": {
          "$oid": "60d21b4667d0d8992e610cb2"
        },
        "quantity": 1,
        "price": 159.99
      }
    ],
    "totalAmount": 159.99,
    "paymentMethod": "CARD",
    "status": "COMPLETED",
    "customerName": "Richard Allen",
    "customerPhone": "555-789-0124",
    "createdAt": "2023-07-25T11:20:00.000Z",
    "user": {
      "$oid": "67d580341d40dbf5dfe6d761"
    }
  },
  {
    "_id": {
      "$oid": "60d21b4667d0d8992e610cd1"
    },
    "orderNumber": "ORD-10018",
    "items": [
      {
        "part": {
          "$oid": "60d21b4667d0d8992e610cb3"
        },
        "quantity": 1,
        "price": 29.99
      },
      {
        "part": {
          "$oid": "60d21b4667d0d8992e610cb8"
        },
        "quantity": 1,
        "price": 19.99
      }
    ],
    "totalAmount": 49.98,
    "paymentMethod": "CASH",
    "status": "COMPLETED",
    "customerName": "Elizabeth Scott",
    "customerPhone": "555-890-1235",
    "createdAt": "2023-07-28T15:45:00.000Z",
    "user": {
      "$oid": "67d580341d40dbf5dfe6d761"
    }
  },
  {
    "_id": {
      "$oid": "60d21b4667d0d8992e610cd2"
    },
    "orderNumber": "ORD-10019",
    "items": [
      {
        "part": {
          "$oid": "60d21b4667d0d8992e610caa"
        },
        "quantity": 2,
        "price": 59.99
      }
    ],
    "totalAmount": 119.98,
    "paymentMethod": "CARD",
    "status": "COMPLETED",
    "customerName": "Thomas Green",
    "customerPhone": "555-901-2346",
    "createdAt": "2023-08-01T10:15:00.000Z",
    "user": {
      "$oid": "67d580341d40dbf5dfe6d761"
    }
  },
  {
    "_id": {
      "$oid": "60d21b4667d0d8992e610cd3"
    },
    "orderNumber": "ORD-10020",
    "items": [
      {
        "part": {
          "$oid": "60d21b4667d0d8992e610cad"
        },
        "quantity": 1,
        "price": 129.99
      }
    ],
    "totalAmount": 129.99,
    "paymentMethod": "CARD",
    "status": "COMPLETED",
    "customerName": "Nancy Baker",
    "customerPhone": "555-012-3457",
    "createdAt": "2023-08-03T13:30:00.000Z",
    "user": {
      "$oid": "67d580341d40dbf5dfe6d761"
    }
  },
  {
    "_id": {
      "$oid": "60d21b4667d0d8992e610cd4"
    },
    "orderNumber": "ORD-10021",
    "items": [
      {
        "part": {
          "$oid": "60d21b4667d0d8992e610ca0"
        },
        "quantity": 1,
        "price": 8.99
      },
      {
        "part": {
          "$oid": "60d21b4667d0d8992e610ca1"
        },
        "quantity": 1,
        "price": 12.99
      },
      {
        "part": {
          "$oid": "60d21b4667d0d8992e610cb4"
        },
        "quantity": 1,
        "price": 24.99
      }
    ],
    "totalAmount": 46.97,
    "paymentMethod": "CASH",
    "status": "COMPLETED",
    "customerName": "William Nelson",
    "customerPhone": "555-123-4569",
    "createdAt": "2023-08-05T09:45:00.000Z",
    "user": {
      "$oid": "67d580341d40dbf5dfe6d761"
    }
  },
  {
    "_id": {
      "$oid": "60d21b4667d0d8992e610cd5"
    },
    "orderNumber": "ORD-10022",
    "items": [
      {
        "part": {
          "$oid": "60d21b4667d0d8992e610ca2"
        },
        "quantity": 1,
        "price": 35.99
      },
      {
        "part": {
          "$oid": "60d21b4667d0d8992e610cb5"
        },
        "quantity": 1,
        "price": 8.99
      }
    ],
    "totalAmount": 44.98,
    "paymentMethod": "CARD",
    "status": "COMPLETED",
    "customerName": "Karen Carter",
    "customerPhone": "555-234-5680",
    "createdAt": "2023-08-08T14:20:00.000Z",
    "user": {
      "$oid": "67d580341d40dbf5dfe6d761"
    }
  },
  {
    "_id": {
      "$oid": "60d21b4667d0d8992e610cd6"
    },
    "orderNumber": "ORD-10023",
    "items": [
      {
        "part": {
          "$oid": "60d21b4667d0d8992e610ca4"
        },
        "quantity": 1,
        "price": 28.99
      },
      {
        "part": {
          "$oid": "60d21b4667d0d8992e610cae"
        },
        "quantity": 1,
        "price": 49.99
      }
    ],
    "totalAmount": 78.98,
    "paymentMethod": "CASH",
    "status": "PENDING",
    "customerName": "Steven Mitchell",
    "customerPhone": "555-345-6781",
    "createdAt": "2023-08-10T11:30:00.000Z",
    "user": {
      "$oid": "67d580341d40dbf5dfe6d761"
    }
  },
  {
    "_id": {
      "$oid": "60d21b4667d0d8992e610cd7"
    },
    "orderNumber": "ORD-10024",
    "items": [
      {
        "part": {
          "$oid": "60d21b4667d0d8992e610cb6"
        },
        "quantity": 1,
        "price": 29.99
      },
      {
        "part": {
          "$oid": "60d21b4667d0d8992e610cb7"
        },
        "quantity": 1,
        "price": 49.99
      }
    ],
    "totalAmount": 79.98,
    "paymentMethod": "CARD",
    "status": "PENDING",
    "customerName": "Linda Roberts",
    "customerPhone": "555-456-7892",
    "createdAt": "2023-08-12T15:45:00.000Z",
    "user": {
      "$oid": "67d580341d40dbf5dfe6d761"
    }
  },
  {
    "_id": {
      "$oid": "60d21b4667d0d8992e610cd8"
    },
    "orderNumber": "ORD-10025",
    "items": [
      {
        "part": {
          "$oid": "60d21b4667d0d8992e610ca5"
        },
        "quantity": 1,
        "price": 89.99
      },
      {
        "part": {
          "$oid": "60d21b4667d0d8992e610ca6"
        },
        "quantity": 1,
        "price": 129.99
      }
    ],
    "totalAmount": 219.98,
    "paymentMethod": "CARD",
    "status": "PENDING",
    "customerName": "Joseph Phillips",
    "customerPhone": "555-567-8903",
    "createdAt": "2023-08-15T10:15:00.000Z",
    "user": {
      "$oid": "67d580341d40dbf5dfe6d761"
    }
  }
]